odoo/addons/sm_reports/__init__.py
odoo/addons/sm_reports/__manifest__.py
odoo/addons/sm_reports/models/__init__.py
odoo/addons/sm_reports/models/models_sm_member.py
odoo/addons/sm_reports/security/ir.model.access.csv
odoo/addons/sm_reports/views/default_template.xml
odoo/addons/sm_reports/views/views_members.xml
odoo11_addon_sm_reports-11.0.0.0.2.dist-info/METADATA
odoo11_addon_sm_reports-11.0.0.0.2.dist-info/WHEEL
odoo11_addon_sm_reports-11.0.0.0.2.dist-info/top_level.txt
odoo11_addon_sm_reports-11.0.0.0.2.dist-info/RECORD
